web_payments/__init__.py
web_payments/_exceptions.py
web_payments/django/__init__.py
web_payments/django/apps.py
web_payments/django/models.py
web_payments/django/signals.py
web_payments/django/urls.py
web_payments/forms.py
web_payments/locale/de/LC_MESSAGES/web_payments.mo
web_payments/locale/de/LC_MESSAGES/web_payments.po
web_payments/locale/it/LC_MESSAGES/web_payments.mo
web_payments/locale/it/LC_MESSAGES/web_payments.po
web_payments/locale/ru/LC_MESSAGES/web_payments.mo
web_payments/locale/ru/LC_MESSAGES/web_payments.po
web_payments/locale/web_payments.pot
web_payments/logic.py
web_payments/status.py
web_payments/testcommon.py
web_payments/translation.py
web_payments/utils.py
web_payments_dummy/__init__.py
web_payments_dummy/django_dummy/__init__.py
web_payments_dummy/django_dummy/apps.py
web_payments_dummy/django_dummy/manage.py
web_payments_dummy/django_dummy/migrations/0001_initial.py
web_payments_dummy/django_dummy/migrations/__init__.py
web_payments_dummy/django_dummy/models.py
web_payments_dummy/django_dummy/settings/.gitignore
web_payments_dummy/django_dummy/settings/__init__.py
web_payments_dummy/django_dummy/settings/test.py
web_payments_dummy/django_dummy/static/w3.css
web_payments_dummy/django_dummy/templates/base.html
web_payments_dummy/django_dummy/templates/form.html
web_payments_dummy/django_dummy/templates/payob.html
web_payments_dummy/django_dummy/urls.py
web_payments_dummy/django_dummy/views.py
web_payments_dummy/django_dummy/wsgi.py
web_payments_dummy/forms.py
web_payments_externalpayments/__init__.py
web_payments_externalpayments/forms.py
web_payments_externalpayments/locale/de/LC_MESSAGES/web_payments.mo
web_payments_externalpayments/locale/de/LC_MESSAGES/web_payments.po
web_payments_externalpayments/locale/web_payments.pot
web_payments_externalpayments/translation.py
web_payments_connector-3.1.0.dist-info/LICENSE.md
web_payments_connector-3.1.0.dist-info/LICENSE.mirumee.md
web_payments_connector-3.1.0.dist-info/METADATA
web_payments_connector-3.1.0.dist-info/WHEEL
web_payments_connector-3.1.0.dist-info/RECORD
